{"data":{"allMarkdownRemark":{"totalCount":4,"edges":[{"node":{"id":"ab9f94f8-85e6-54db-afb7-d0ad9e011f90","frontmatter":{"title":"Hola mundo","date":"03 February, 2018"},"excerpt":"QUe onda vatos como han estado ","html":"<p>QUe onda vatos como han estado </p>\n<img src='https://i.ytimg.com/vi/uoQLXUT9PZo/maxresdefault.jpg' />"}},{"node":{"id":"b9b22ed5-b90e-5ea8-a0e5-83788067a72a","frontmatter":{"title":"Sweet Pandas Eating Sweets","date":"10 August, 2017"},"excerpt":"Pandas are really sweet. Here's a video of a panda eating sweets.","html":"<p>Pandas are really sweet.</p>\n<p>Here's a video of a panda eating sweets.</p>\n<iframe width=\"560\" height=\"315\" src=\"https://www.youtube.com/embed/4n0xNbfJLR8\" frameborder=\"0\" allowfullscreen></iframe>"}},{"node":{"id":"85284755-fd23-5611-ae81-dd73f8879c25","frontmatter":{"title":"Pandas and Bananas","date":"21 August, 2017"},"excerpt":"Do Pandas eat bananas? Check out this short video that shows that yes! pandas do\nseem to really enjoy bananas!","html":"<p>Do Pandas eat bananas? Check out this short video that shows that yes! pandas do\nseem to really enjoy bananas!</p>\n<iframe width=\"560\" height=\"315\" src=\"https://www.youtube.com/embed/4SZl1r2O_bY\" frameborder=\"0\" allowfullscreen></iframe>"}},{"node":{"id":"5e3fa145-a9cd-596d-8f04-b196f904eee4","frontmatter":{"title":"californis","date":"03 February, 2018"},"excerpt":"calois  ahah","html":"<p>calois </p>\n<p>ahah</p>\n<img src='https://i.ytimg.com/vi/uoQLXUT9PZo/maxresdefault.jpg' />"}}]}},"pageContext":{"slug":"/ssoso/"}}